{
	"nameShort": "Code - OSS",
	"nameLong": "Code - OSS",
	"applicationName": "code-oss",
	"dataFolderName": ".vscode-oss",
	"win32MutexName": "vscodeoss",
	"licenseName": "MIT",
	"licenseUrl": "https://github.com/Microsoft/vscode/blob/master/LICENSE.txt",
	"win32DirName": "Microsoft Code OSS",
	"win32NameVersion": "Microsoft Code OSS",
	"win32RegValueName": "CodeOSS",
	"win32AppId": "{{E34003BB-9E10-4501-8C11-BE3FAA83F23F}",
	"win32x64AppId": "{{D77B7E06-80BA-4137-BCF4-654B95CCEBC5}",
	"win32arm64AppId": "{{D1ACE434-89C5-48D1-88D3-E2991DF85475}",
	"win32UserAppId": "{{C6065F05-9603-4FC4-8101-B9781A25D88E}",
	"win32x64UserAppId": "{{CC6B787D-37A0-49E8-AE24-8559A032BE0C}",
	"win32arm64UserAppId": "{{3AEBF0C8-F733-4AD4-BADE-FDB816D53D7B}",
	"win32AppUserModelId": "Microsoft.CodeOSS",
	"win32ShellNameShort": "C&ode - OSS",
	"darwinBundleIdentifier": "com.visualstudio.code.oss",
	"linuxIconName": "com.visualstudio.code.oss",
	"licenseFileName": "LICENSE.txt",
	"reportIssueUrl": "https://github.com/Microsoft/vscode/issues/new",
	"urlProtocol": "code-oss",
	"extensionAllowedProposedApi": [
		"ms-vscode.vscode-js-profile-flame",
		"ms-vscode.vscode-js-profile-table",
		"ms-vscode.references-view",
		"ms-vscode.github-browser"
	],
	"builtInExtensions": [
		{
			"name": "ms-vscode.node-debug",
			"version": "1.44.11",
			"repo": "https://github.com/Microsoft/vscode-node-debug",
			"metadata": {
				"id": "b6ded8fb-a0a0-4c1c-acbd-ab2a3bc995a6",
				"publisherId": {
					"publisherId": "5f5636e7-69ed-4afe-b5d6-8d231fb3d3ee",
					"publisherName": "ms-vscode",
					"displayName": "Microsoft",
					"flags": "verified"
				},
				"publisherDisplayName": "Microsoft"
			}
		},
		{
			"name": "ms-vscode.node-debug2",
			"version": "1.42.5",
			"repo": "https://github.com/Microsoft/vscode-node-debug2",
			"metadata": {
				"id": "36d19e17-7569-4841-a001-947eb18602b2",
				"publisherId": {
					"publisherId": "5f5636e7-69ed-4afe-b5d6-8d231fb3d3ee",
					"publisherName": "ms-vscode",
					"displayName": "Microsoft",
					"flags": "verified"
				},
				"publisherDisplayName": "Microsoft"
			}
		},
		{
			"name": "ms-vscode.references-view",
			"version": "0.0.62",
			"repo": "https://github.com/Microsoft/vscode-reference-view",
			"metadata": {
				"id": "dc489f46-520d-4556-ae85-1f9eab3c412d",
				"publisherId": {
					"publisherId": "5f5636e7-69ed-4afe-b5d6-8d231fb3d3ee",
					"publisherName": "ms-vscode",
					"displayName": "Microsoft",
					"flags": "verified"
				},
				"publisherDisplayName": "Microsoft"
			}
		},
		{
			"name": "ms-vscode.js-debug-companion",
			"version": "1.0.7",
			"repo": "https://github.com/microsoft/vscode-js-debug-companion",
			"metadata": {
				"id": "99cb0b7f-7354-4278-b8da-6cc79972169d",
				"publisherId": {
					"publisherId": "5f5636e7-69ed-4afe-b5d6-8d231fb3d3ee",
					"publisherName": "ms-vscode",
					"displayName": "Microsoft",
					"flags": "verified"
				},
				"publisherDisplayName": "Microsoft"
			}
		},
		{
			"name": "ms-vscode.js-debug",
			"version": "1.49.5",
			"repo": "https://github.com/Microsoft/vscode-js-debug",
			"metadata": {
				"id": "25629058-ddac-4e17-abba-74678e126c5d",
				"publisherId": {
					"publisherId": "5f5636e7-69ed-4afe-b5d6-8d231fb3d3ee",
					"publisherName": "ms-vscode",
					"displayName": "Microsoft",
					"flags": "verified"
				},
				"publisherDisplayName": "Microsoft"
			}
		},
		{
			"name": "ms-vscode.vscode-js-profile-table",
			"version": "0.0.6",
			"repo": "https://github.com/Microsoft/vscode-js-debug",
			"metadata": {
				"id": "7e52b41b-71ad-457b-ab7e-0620f1fc4feb",
				"publisherId": {
					"publisherId": "5f5636e7-69ed-4afe-b5d6-8d231fb3d3ee",
					"publisherName": "ms-vscode",
					"displayName": "Microsoft",
					"flags": "verified"
				},
				"publisherDisplayName": "Microsoft"
			}
		}
	],
	"webBuiltInExtensions": [
		{
			"name": "ms-vscode.github-browser",
			"version": "0.0.7",
			"repo": "https://github.com/Microsoft/vscode-github-browser",
			"metadata": {
				"id": "c1bcff4b-4ecb-466e-b8f6-b02788b5fb5a",
				"publisherId": {
					"publisherId": "5f5636e7-69ed-4afe-b5d6-8d231fb3d3ee",
					"publisherName": "ms-vscode",
					"displayName": "Microsoft",
					"flags": "verified"
				},
				"publisherDisplayName": "Microsoft"
			}
		}
	]
}
